mimecat.py
setup.py
mimecat.egg-info/PKG-INFO
mimecat.egg-info/SOURCES.txt
mimecat.egg-info/dependency_links.txt
mimecat.egg-info/top_level.txt