Metadata-Version: 1.1
Name: mimecat
Version: 0.1.1
Summary: A simple module for handling a catalogue of MIME types and extensions
Home-page: https://github.com/mizhi/mimecat
Author: Mitchell Peabody
Author-email: UNKNOWN
License: MIT
Keywords: MIME types extensions
Platform: UNKNOWN
Classifier: Development Status :: 3 - Alpha
Classifier: License :: OSI Approved :: MIT License
Classifier: Topic :: Internet
Classifier: Topic :: Internet :: WWW/HTTP
Classifier: Topic :: Software Development
